dpsql/__init__.py
dpsql/table/__init__.py
dpsql/table/helpers/__init__.py
dpsql/table/helpers/table_col_name.py
dpsql/table/model/__init__.py
dpsql/table/model/case_obj.py
dpsql/table/model/criterion_obj.py
dpsql/table/model/db_objects.py
dpsql/table/model/func_aggregate.py
dpsql/table/model/func_db.py
dpsql/table/model/select_obj.py
dpsql/table/model/statement_obj.py
dpsql/table/service/__init__.py
datapenosql-0.4.dist-info/LICENSE
datapenosql-0.4.dist-info/METADATA
datapenosql-0.4.dist-info/WHEEL
datapenosql-0.4.dist-info/top_level.txt
datapenosql-0.4.dist-info/RECORD
