Metadata-Version: 2.1
Name: datapenosql
Version: 0.4
Summary: DataPeno SQL Query Builder Utility
Home-page: https://github.com/compufreq/datapenosql.git
Author: Alaa Alhorani
Author-email: alaa.alhorani@outlook.com
License: MIT License
Platform: UNKNOWN
Classifier: Programming Language :: Python :: 3.6
Classifier: Programming Language :: Python :: 3.7
Classifier: Programming Language :: Python :: 3.9
Classifier: Operating System :: OS Independent
Requires-Python: >=3.6
License-File: LICENSE
